pynguin/__init__.py
pynguin/__main__.py
pynguin/__version__.py
pynguin/analyses/__init__.py
pynguin/analyses/constants.py
pynguin/analyses/module.py
pynguin/analyses/modulecomplexity.py
pynguin/analyses/seeding.py
pynguin/analyses/string_subtypes.py
pynguin/analyses/syntaxtree.py
pynguin/analyses/type_inference.py
pynguin/analyses/typesystem.py
pynguin/assertion/__init__.py
pynguin/assertion/assertion.py
pynguin/assertion/assertion_to_ast.py
pynguin/assertion/assertion_trace.py
pynguin/assertion/assertiongenerator.py
pynguin/assertion/assertiontraceobserver.py
pynguin/assertion/llmassertiongenerator.py
pynguin/assertion/mutation_analysis/__init__.py
pynguin/assertion/mutation_analysis/controller.py
pynguin/assertion/mutation_analysis/mutators.py
pynguin/assertion/mutation_analysis/operators/__init__.py
pynguin/assertion/mutation_analysis/operators/arithmetic.py
pynguin/assertion/mutation_analysis/operators/base.py
pynguin/assertion/mutation_analysis/operators/decorator.py
pynguin/assertion/mutation_analysis/operators/exception.py
pynguin/assertion/mutation_analysis/operators/inheritance.py
pynguin/assertion/mutation_analysis/operators/logical.py
pynguin/assertion/mutation_analysis/operators/loop.py
pynguin/assertion/mutation_analysis/operators/misc.py
pynguin/assertion/mutation_analysis/strategies.py
pynguin/assertion/mutation_analysis/transformer.py
pynguin/cli.py
pynguin/configuration.py
pynguin/ga/__init__.py
pynguin/ga/algorithms/__init__.py
pynguin/ga/algorithms/abstractmosaalgorithm.py
pynguin/ga/algorithms/archive.py
pynguin/ga/algorithms/dynamosaalgorithm.py
pynguin/ga/algorithms/generationalgorithm.py
pynguin/ga/algorithms/llmosalgorithm.py
pynguin/ga/algorithms/mioalgorithm.py
pynguin/ga/algorithms/mosaalgorithm.py
pynguin/ga/algorithms/randomalgorithm.py
pynguin/ga/algorithms/randomsearchalgorithm.py
pynguin/ga/algorithms/wholesuitealgorithm.py
pynguin/ga/chromosome.py
pynguin/ga/chromosomefactory.py
pynguin/ga/chromosomevisitor.py
pynguin-0.44.0.dist-info/LICENSE.rst
pynguin-0.44.0.dist-info/LICENSES/Apache-2.0.txt
pynguin-0.44.0.dist-info/LICENSES/BSD-2-Clause.txt
pynguin-0.44.0.dist-info/LICENSES/CC-BY-4.0.txt
pynguin-0.44.0.dist-info/LICENSES/CC0-1.0.txt
pynguin-0.44.0.dist-info/LICENSES/MIT.txt
pynguin-0.44.0.dist-info/METADATA
pynguin-0.44.0.dist-info/WHEEL
pynguin-0.44.0.dist-info/entry_points.txt
pynguin-0.44.0.dist-info/RECORD
