Metadata-Version: 2.3
Name: pynguin
Version: 0.44.0
Summary: Pynguin is a tool for automated unit test generation for Python
License: MIT
Keywords: unit test,random testing,search based,test generation
Author: Stephan Lukasczyk
Author-email: stephan@pynguin.eu
Requires-Python: >=3.10,<3.15
Classifier: Development Status :: 3 - Alpha
Classifier: Environment :: Console
Classifier: Intended Audience :: Developers
Classifier: Intended Audience :: Education
Classifier: Intended Audience :: Science/Research
Classifier: License :: OSI Approved :: MIT License
Classifier: Operating System :: MacOS :: MacOS X
Classifier: Operating System :: Microsoft :: Windows
Classifier: Operating System :: POSIX :: Linux
Classifier: Programming Language :: Python :: 3
Classifier: Programming Language :: Python :: 3.10
Classifier: Programming Language :: Python :: 3.11
Classifier: Programming Language :: Python :: 3.12
Classifier: Programming Language :: Python :: 3.13
Classifier: Programming Language :: Python :: 3.14
Classifier: Programming Language :: Python :: Implementation :: CPython
Classifier: Topic :: Education :: Testing
Classifier: Topic :: Software Development :: Testing
Classifier: Topic :: Software Development :: Testing :: Unit
Classifier: Typing :: Typed
Provides-Extra: fandango-faker
Provides-Extra: numpy
Provides-Extra: openai
Provides-Extra: typing
Requires-Dist: Jinja2 (>=3.1.6,<4.0.0)
Requires-Dist: Pygments (>=2.19.2,<3.0.0)
Requires-Dist: asciitree (>=0.3.3,<0.4.0)
Requires-Dist: astroid (>=4.0.1,<5.0.0)
Requires-Dist: black (>=25.1.0,<26.0.0)
Requires-Dist: bytecode (==0.17.0)
Requires-Dist: dill (>=0.4.0,<0.5.0)
Requires-Dist: faker (>=37.3.0,<38.0.0) ; extra == "fandango-faker"
Requires-Dist: fandango-fuzzer (>=0.8.2,<0.9.0) ; extra == "fandango-faker"
Requires-Dist: libcst (>=1.7.0,<2.0.0)
Requires-Dist: multiprocess (>=0.70.18,<0.71.0)
Requires-Dist: mypy (>=1.15.0,<2.0.0) ; extra == "typing"
Requires-Dist: networkx (>=3.4.2,<4.0.0)
Requires-Dist: numpy (>=1.26.4,<2.0.0) ; extra == "numpy"
Requires-Dist: openai (>=1.72.0,<2.0.0) ; extra == "openai"
Requires-Dist: psutil (>=7.1.1,<8.0.0)
Requires-Dist: pytest (>=8.3.5,<9.0.0)
Requires-Dist: rich (>=14.0.0,<15.0.0)
Requires-Dist: rstr (>=3.2.2,<4.0.0)
Requires-Dist: setuptools (>=80.9.0,<81.0.0)
Requires-Dist: simple-parsing (>=0.1.7,<0.2.0)
Requires-Dist: toml (>=0.10.2,<0.11.0)
Requires-Dist: typing-extensions (>=4.12.2,<5.0.0) ; extra == "typing"
Requires-Dist: typing_inspect (>=0.9.0,<0.10.0)
Requires-Dist: xmltodict (>=0.14.2,<0.15.0) ; extra == "fandango-faker"
Project-URL: Documentation, https://pynguin.readthedocs.io
Project-URL: Homepage, https://www.pynguin.eu
Project-URL: Repository, https://github.com/se2p/pynguin
